LICENSE
README.md
asanai.py
pyproject.toml
requirements.txt
setup.cfg
asanAI.egg-info/PKG-INFO
asanAI.egg-info/SOURCES.txt
asanAI.egg-info/dependency_links.txt
asanAI.egg-info/requires.txt
asanAI.egg-info/top_level.txt
asanai-426.data/data/bin/LICENSE
asanai-426.data/data/bin/asanai.py
asanai-426.data/data/bin/requirements.txt
asanai-426.data/data/bin/setup.py
asanai-426.dist-info/licenses/LICENSE
asanai-426.dist-info/METADATA
asanai-426.dist-info/WHEEL
asanai-426.dist-info/top_level.txt
asanai-426.dist-info/RECORD
