Metadata-Version: 2.4
Name: asanAI
Version: 426
Summary: Tools to help with the scripts created by asanAI
Home-page: https://asanai.scads.ai/
Author: Norman Koch
Author-email: norman.koch@tu-dresden.de
Platform: Linux
License-File: LICENSE
Requires-Dist: protobuf
Requires-Dist: beartype
Requires-Dist: scikit-image
Requires-Dist: numpy
Requires-Dist: opencv-python
Requires-Dist: rich
Requires-Dist: psutil
Requires-Dist: keras
Dynamic: home-page
Dynamic: license-file
Dynamic: platform
